athena_km_neo4j/Invoker.py
athena_km_neo4j/NeoSdkInitialize.py
athena_km_neo4j/URLConstant.py
athena_km_neo4j/__init__.py
athena_km_neo4j-0.1.2.dist-info/LICENSE.txt
athena_km_neo4j-0.1.2.dist-info/METADATA
athena_km_neo4j-0.1.2.dist-info/WHEEL
athena_km_neo4j-0.1.2.dist-info/top_level.txt
athena_km_neo4j-0.1.2.dist-info/RECORD
