Metadata-Version: 2.1
Name: athena-km-neo4j
Version: 0.1.2
Summary: km neo4j sdk
Home-page: UNKNOWN
Author: Bwl
License: UNKNOWN
Platform: UNKNOWN
License-File: LICENSE.txt
